opticulator/__init__.py
opticulator/peak/__init__.py
opticulator/peak/peak_analyzer.py
opticulator-0.2.0.dist-info/licenses/LICENSE
opticulator-0.2.0.dist-info/METADATA
opticulator-0.2.0.dist-info/WHEEL
opticulator-0.2.0.dist-info/top_level.txt
opticulator-0.2.0.dist-info/RECORD
